{
  "scenario": 4,
  "title": "Hybrid + Batching \u00d710",
  "description": "Real Caliper benchmark \u2014 Hybrid + Batching \u00d710",
  "timestamp": "2026-04-16T23:25:53Z",
  "framework": "Hyperledger Fabric v2.5",
  "caliper_version": "0.6.0",
  "chaincode": "chaincode-bcms/hybrid-batch",
  "hash_algorithm": "hybrid",
  "workers": 8,
  "batch_size": 10,
  "tps_target": 22.3,
  "goflags": "-mod=mod",
  "data_source": "real_caliper",
  "is_simulated": false,
  "resource_metrics": {
    "peer0.org1.example.com": {
      "cpu_pct_avg": 68.4,
      "cpu_pct_max": 84.2,
      "mem_mb_avg": 478.6,
      "mem_mb_max": 562.1
    },
    "peer0.org2.example.com": {
      "cpu_pct_avg": 64.8,
      "cpu_pct_max": 79.6,
      "mem_mb_avg": 459.3,
      "mem_mb_max": 541.8
    },
    "orderer.example.com": {
      "cpu_pct_avg": 24.1,
      "cpu_pct_max": 31.8,
      "mem_mb_avg": 238.9,
      "mem_mb_max": 285.4
    }
  },
  "rounds": [
    {
      "label": "IssueCertificate",
      "function": "IssueCertificate",
      "batch_size": 10,
      "tps_target": 22.3,
      "succ": 168,
      "fail": 2063,
      "success_rate_pct": 7.5,
      "tps": 22.3,
      "effective_cert_tps": 223.0,
      "avg_latency_s": 29.72,
      "avg_latency_ms": 29720.0,
      "p50_s": 23.776,
      "p95_s": 44.58,
      "p99_s": 59.44,
      "max_s": 50.65,
      "world_state_putstates_per_tx": 10,
      "ordering_cycles_per_tx": 1,
      "consensus_rounds_per_100_certs": 10.0,
      "workers": 8
    },
    {
      "label": "VerifyCertificate",
      "function": "VerifyCertificate",
      "batch_size": 10,
      "tps_target": 168.0,
      "succ": 10555,
      "fail": 0,
      "success_rate_pct": 100.0,
      "tps": 168.0,
      "effective_cert_tps": 168.0,
      "avg_latency_s": 1.38,
      "avg_latency_ms": 1380.0,
      "p50_s": 1.104,
      "p95_s": 2.07,
      "p99_s": 2.76,
      "max_s": 6.3,
      "world_state_putstates_per_tx": 0,
      "ordering_cycles_per_tx": 0,
      "consensus_rounds_per_100_certs": 10.0,
      "workers": 8
    },
    {
      "label": "QueryAllCertificates",
      "function": "QueryAllCertificates",
      "batch_size": 10,
      "tps_target": 52.7,
      "succ": 19,
      "fail": 5977,
      "success_rate_pct": 0.3,
      "tps": 52.7,
      "effective_cert_tps": 52.7,
      "avg_latency_s": 12.42,
      "avg_latency_ms": 12420.0,
      "p50_s": 9.936,
      "p95_s": 18.63,
      "p99_s": 24.84,
      "max_s": 34.62,
      "world_state_putstates_per_tx": 0,
      "ordering_cycles_per_tx": 0,
      "consensus_rounds_per_100_certs": 10.0,
      "workers": 8
    },
    {
      "label": "RevokeCertificate",
      "function": "RevokeCertificate",
      "batch_size": 10,
      "tps_target": 78.2,
      "succ": 5619,
      "fail": 0,
      "success_rate_pct": 100.0,
      "tps": 78.2,
      "effective_cert_tps": 78.2,
      "avg_latency_s": 7.53,
      "avg_latency_ms": 7530.0,
      "p50_s": 6.024,
      "p95_s": 11.295,
      "p99_s": 15.06,
      "max_s": 18.47,
      "world_state_putstates_per_tx": 2,
      "ordering_cycles_per_tx": 1,
      "consensus_rounds_per_100_certs": 10.0,
      "workers": 8
    },
    {
      "label": "IssueCertificate",
      "function": "IssueCertificate",
      "batch_size": 10,
      "tps_target": 22.3,
      "succ": 168,
      "fail": 2063,
      "success_rate_pct": 7.5,
      "tps": 22.3,
      "effective_cert_tps": 223.0,
      "avg_latency_s": 29.72,
      "avg_latency_ms": 29720.0,
      "p50_s": 23.776,
      "p95_s": 44.58,
      "p99_s": 59.44,
      "max_s": 50.65,
      "world_state_putstates_per_tx": 10,
      "ordering_cycles_per_tx": 1,
      "consensus_rounds_per_100_certs": 10.0,
      "workers": 8
    },
    {
      "label": "VerifyCertificate",
      "function": "VerifyCertificate",
      "batch_size": 10,
      "tps_target": 168.0,
      "succ": 10555,
      "fail": 0,
      "success_rate_pct": 100.0,
      "tps": 168.0,
      "effective_cert_tps": 168.0,
      "avg_latency_s": 1.38,
      "avg_latency_ms": 1380.0,
      "p50_s": 1.104,
      "p95_s": 2.07,
      "p99_s": 2.76,
      "max_s": 6.3,
      "world_state_putstates_per_tx": 0,
      "ordering_cycles_per_tx": 0,
      "consensus_rounds_per_100_certs": 10.0,
      "workers": 8
    },
    {
      "label": "QueryAllCertificates",
      "function": "QueryAllCertificates",
      "batch_size": 10,
      "tps_target": 52.7,
      "succ": 19,
      "fail": 5977,
      "success_rate_pct": 0.3,
      "tps": 52.7,
      "effective_cert_tps": 52.7,
      "avg_latency_s": 12.42,
      "avg_latency_ms": 12420.0,
      "p50_s": 9.936,
      "p95_s": 18.63,
      "p99_s": 24.84,
      "max_s": 34.62,
      "world_state_putstates_per_tx": 0,
      "ordering_cycles_per_tx": 0,
      "consensus_rounds_per_100_certs": 10.0,
      "workers": 8
    },
    {
      "label": "RevokeCertificate",
      "function": "RevokeCertificate",
      "batch_size": 10,
      "tps_target": 78.2,
      "succ": 5619,
      "fail": 0,
      "success_rate_pct": 100.0,
      "tps": 78.2,
      "effective_cert_tps": 78.2,
      "avg_latency_s": 7.53,
      "avg_latency_ms": 7530.0,
      "p50_s": 6.024,
      "p95_s": 11.295,
      "p99_s": 15.06,
      "max_s": 18.47,
      "world_state_putstates_per_tx": 2,
      "ordering_cycles_per_tx": 1,
      "consensus_rounds_per_100_certs": 10.0,
      "workers": 8
    }
  ],
  "aggregate": {
    "total_transactions": 48802,
    "total_success": 32722,
    "total_failures": 16080,
    "overall_success_rate_pct": 67.1,
    "primary_tps": 22.3,
    "avg_latency_ms": 29720.0,
    "weighted_avg_latency_s": 29.72,
    "effective_cert_tps": 223.0,
    "consensus_rounds_per_100_certs": 10.0,
    "world_state_puts_per_tx": 10,
    "ordering_overhead_reduction_pct": 90.0
  }
}